[
  {
    "type": "key",
    "event": "up",
    "name": "f1",
    "time": 0.059052467346191406
  },
  {
    "type": "key",
    "event": "down",
    "name": "d",
    "time": 0.6745171546936035
  },
  {
    "type": "key",
    "event": "up",
    "name": "d",
    "time": 0.6912851333618164
  },
  {
    "type": "key",
    "event": "down",
    "name": "d",
    "time": 0.7065744400024414
  },
  {
    "type": "key",
    "event": "down",
    "name": "space",
    "time": 0.978682279586792
  },
  {
    "type": "key",
    "event": "up",
    "name": "space",
    "time": 1.0985493659973145
  },
  {
    "type": "key",
    "event": "down",
    "name": "space",
    "time": 1.9469811916351318
  },
  {
    "type": "key",
    "event": "up",
    "name": "space",
    "time": 2.066610813140869
  },
  {
    "type": "key",
    "event": "down",
    "name": "space",
    "time": 2.5865864753723145
  },
  {
    "type": "key",
    "event": "up",
    "name": "space",
    "time": 2.706713914871216
  },
  {
    "type": "key",
    "event": "down",
    "name": "space",
    "time": 3.210477828979492
  },
  {
    "type": "key",
    "event": "up",
    "name": "space",
    "time": 3.3547263145446777
  },
  {
    "type": "key",
    "event": "down",
    "name": "space",
    "time": 4.058889389038086
  },
  {
    "type": "key",
    "event": "up",
    "name": "space",
    "time": 4.195419549942017
  },
  {
    "type": "key",
    "event": "down",
    "name": "space",
    "time": 5.050555467605591
  },
  {
    "type": "key",
    "event": "up",
    "name": "space",
    "time": 5.170609951019287
  },
  {
    "type": "key",
    "event": "up",
    "name": "d",
    "time": 7.098474740982056
  },
  {
    "type": "key",
    "event": "down",
    "name": "d",
    "time": 7.114481210708618
  },
  {
    "type": "key",
    "event": "up",
    "name": "d",
    "time": 7.186478137969971
  },
  {
    "type": "key",
    "event": "down",
    "name": "f3",
    "time": 8.442570686340332
  }
]